ssh_cluster/__init__.py
ssh_cluster/cluster.py
ssh_cluster/connection.py
ssh_cluster/types.py
ssh_clusters_manager-0.1.0.dist-info/LICENSE
ssh_clusters_manager-0.1.0.dist-info/METADATA
ssh_clusters_manager-0.1.0.dist-info/WHEEL
ssh_clusters_manager-0.1.0.dist-info/RECORD
