Metadata-Version: 2.3
Name: ssh-clusters-manager
Version: 0.1.0
Summary: Lightweight Python library for parallel SSH operations
License: MIT
Keywords: ssh,parallel,cluster,automation
Author: garv.works@outlook.com
Requires-Python: >=3.9
Classifier: License :: OSI Approved :: MIT License
Classifier: Operating System :: OS Independent
Classifier: Programming Language :: Python :: 3
Classifier: Programming Language :: Python :: 3.9
Classifier: Programming Language :: Python :: 3.10
Classifier: Programming Language :: Python :: 3.11
Classifier: Programming Language :: Python :: 3.12
Classifier: Programming Language :: Python :: 3.13
Requires-Dist: PyYAML (>=6.0)
Requires-Dist: bcrypt (==4.0.1)
Requires-Dist: cffi (==1.15.1)
Requires-Dist: cryptography (==41.0.7)
Requires-Dist: paramiko (>=3.5.1,<4.0.0)
Requires-Dist: pycparser (==2.21)
Project-URL: Homepage, https://github.com/goravaa/SSHManager
Project-URL: Repository, https://github.com/goravaa/SSHManager
